smalld/__init__.py
smalld/exceptions.py
smalld/gateway.py
smalld/json_elements.py
smalld/logger.py
smalld/ratelimit.py
smalld/smalld.py
smalld/standard_listeners.py
smalld/resources/__init__.py
smalld/resources/ratelimit_buckets
smalld-0.3.0.dist-info/LICENSE
smalld-0.3.0.dist-info/METADATA
smalld-0.3.0.dist-info/WHEEL
smalld-0.3.0.dist-info/top_level.txt
smalld-0.3.0.dist-info/RECORD
