Metadata-Version: 2.1
Name: smalld
Version: 0.3.0
Summary: A minimalist python client for the Discord API
Home-page: https://github.com/princesslana/smalld.py
Author: Princess Lana
Author-email: ianagbip1oti@gmail.com
License: MIT
Platform: UNKNOWN
Classifier: Development Status :: 4 - Beta
Classifier: Intended Audience :: Developers
Classifier: License :: OSI Approved :: MIT License
Classifier: Programming Language :: Python :: 3
Classifier: Programming Language :: Python :: 3.6
Classifier: Programming Language :: Python :: 3.7
Classifier: Programming Language :: Python :: 3.8
Requires-Dist: requests (>=2.23.0)
Requires-Dist: websocket-client (>=0.57.0)
